project_scanner-2025.5.181939.dist-info/licenses/LICENSE
projectscanner/__init__.py
projectscanner/scanner.py
project_scanner-2025.5.181939.dist-info/METADATA
project_scanner-2025.5.181939.dist-info/WHEEL
project_scanner-2025.5.181939.dist-info/top_level.txt
project_scanner-2025.5.181939.dist-info/RECORD
