Metadata-Version: 2.4
Name: project-scanner
Version: 2025.5.181939
Summary: A Python package to scan project directories and files batch by batch.
Home-page: https://github.com/chigwell/project-scanner
Author: Eugene Evstafev
Author-email: chigwel@gmail.com
Classifier: Programming Language :: Python :: 3
Classifier: License :: OSI Approved :: MIT License
Classifier: Operating System :: OS Independent
Requires-Python: >=3.6
License-File: LICENSE
Dynamic: author
Dynamic: author-email
Dynamic: classifier
Dynamic: description
Dynamic: description-content-type
Dynamic: home-page
Dynamic: license-file
Dynamic: requires-python
Dynamic: summary
